LICENSE
MANIFEST.in
README
README.md
README.txt
ez_setup.py
setup.py
pyAniSort.egg-info/PKG-INFO
pyAniSort.egg-info/SOURCES.txt
pyAniSort.egg-info/dependency_links.txt
pyAniSort.egg-info/entry_points.txt
pyAniSort.egg-info/top_level.txt
pyanisort/__init__.py
pyanisort/findtitle.py
pyanisort/main.py
pyanisort/seriesmatch.py
pyanisort/utilities.py
pyanisort/conf/logger.conf
pyanisort/logs/pyAniSort.log