Metadata-Version: 1.1
Name: pyAniSort
Version: 1.0
Summary: Automatically sorts anime using information from anidb.net
Home-page: https://github.com/jotaro0010/pyanisort
Author: Jeremy Ottesen
Author-email: jotaro0010@gmail.com
License: MIT Software License
Platform: any
Classifier: Development Status :: 3 - Alpha
Classifier: Programming Language :: Python
Classifier: License :: OSI Approved :: MIT License
Classifier: Environment :: Console
Classifier: Intended Audience :: End Users/Desktop
